surgeon_pytorch/__init__.py
surgeon_pytorch/extract.py
surgeon_pytorch/inspect.py
surgeon_pytorch/utils.py
surgeon_pytorch-0.0.4.dist-info/LICENSE
surgeon_pytorch-0.0.4.dist-info/METADATA
surgeon_pytorch-0.0.4.dist-info/WHEEL
surgeon_pytorch-0.0.4.dist-info/top_level.txt
surgeon_pytorch-0.0.4.dist-info/RECORD
